modapi/__init__.py
modapi/__main__.py
modapi/api/__init__.py
modapi/api/cmd.py
modapi/api/mqtt.py
modapi/api/rest.py
modapi/api/rtu.py
modapi/api/shell.py
modapi/api/tcp.py
modapi/api/ws.py
modapi/baudrates.json
modapi/cli.py
modapi/config.py
modapi/constants.json
modapi/rtu/__init__.py
modapi/rtu/base.py
modapi/rtu/client.py
modapi/rtu/crc.py
modapi/rtu/device_manager.py
modapi/rtu/device_state.py
modapi/rtu/devices.py
modapi/rtu/protocol.py
modapi/rtu/utils.py
modapi-0.2.4.dist-info/LICENSE
modapi-0.2.4.dist-info/METADATA
modapi-0.2.4.dist-info/WHEEL
modapi-0.2.4.dist-info/entry_points.txt
modapi-0.2.4.dist-info/RECORD
